zerk/__init__.py
zerk/clocked.py
zerk/console.py
zerk/decoder.py
zerk/default.py
zerk/encoder.py
zerk/handler.py
zerk/listens.py
zerk/message.py
zerk/objects.py
zerk/storage.py
zerk/threads.py
zerk/utility.py
zerk/modules/__init__.py
zerk/modules/cmd.py
zerk/modules/dbg.py
zerk/modules/flt.py
zerk/modules/fnd.py
zerk/modules/irc.py
zerk/modules/log.py
zerk/modules/opt.py
zerk/modules/req.py
zerk/modules/rss.py
zerk/modules/tdo.py
zerk/modules/thr.py
zerk/modules/upt.py
zerk/modules/usr.py
zerk/modules/wsd.py
zerk-1.data/scripts/zerk
zerk-1.dist-info/METADATA
zerk-1.dist-info/WHEEL
zerk-1.dist-info/top_level.txt
zerk-1.dist-info/RECORD
